LICENSE.txt
MANIFEST.in
README.txt
setup.py
pcart_wishlist/__init__.py
pcart_wishlist/admin.py
pcart_wishlist/apps.py
pcart_wishlist/models.py
pcart_wishlist/urls.py
pcart_wishlist/views.py
pcart_wishlist.egg-info/PKG-INFO
pcart_wishlist.egg-info/SOURCES.txt
pcart_wishlist.egg-info/dependency_links.txt
pcart_wishlist.egg-info/not-zip-safe
pcart_wishlist.egg-info/requires.txt
pcart_wishlist.egg-info/top_level.txt
pcart_wishlist/locale/ru/LC_MESSAGES/django.mo
pcart_wishlist/locale/ru/LC_MESSAGES/django.po
pcart_wishlist/locale/uk/LC_MESSAGES/django.mo
pcart_wishlist/locale/uk/LC_MESSAGES/django.po
pcart_wishlist/migrations/0001_initial.py
pcart_wishlist/migrations/0002_auto_20170921_1253.py
pcart_wishlist/migrations/__init__.py