Metadata-Version: 1.0
Name: pcart-wishlist
Version: 1.99.2
Summary: A powerful e-commerce solution for Django CMS
Home-page: http://the7bits.com/
Author: Oleh Korkh
Author-email: oleh.korkh@the7bits.com
License: BSD License
Platform: OS Independent
